{
  "term": "Supply",
  "total_results": 11,
  "processed_count": 11,
  "discarded_count": 0,
  "items": [
    {
      "doi": "10.1038/165761a0",
      "title": [
        "Supply and Demand for Physicists"
      ],
      "type": "journal-article",
      "container-title": [
        "Nature"
      ],
      "subject": [],
      "abstract": "",
      "publication_date": "1950-05"
    },
    {
      "doi": "10.2307/2549385",
      "title": [
        "United Kingdom Public Expenditure by Votes of Supply, 1793-1817"
      ],
      "type": "journal-article",
      "container-title": [
        "Economica"
      ],
      "subject": [],
      "abstract": "",
      "publication_date": "1950-05"
    },
    {
      "doi": "10.2113/gsecongeo.45.3.245",
      "title": [
        "Labratory power supply for vibrator-type portable Geiger counters"
      ],
      "type": "journal-article",
      "container-title": [
        "Economic Geology"
      ],
      "subject": [],
      "abstract": "",
      "publication_date": "1950-05"
    },
    {
      "doi": "10.1063/1.1745628",
      "title": [
        "Power Supply for the Cenco Concentrated-Arc Lamp"
      ],
      "type": "journal-article",
      "container-title": [
        "Review of Scientific Instruments"
      ],
      "subject": [],
      "abstract": "",
      "publication_date": "1950-05"
    },
    {
      "doi": "10.2307/1927654",
      "title": [
        "A Note on the Supply of Female Labor"
      ],
      "type": "journal-article",
      "container-title": [
        "The Review of Economics and Statistics"
      ],
      "subject": [],
      "abstract": "",
      "publication_date": "1950-05"
    },
    {
      "doi": "10.2307/137986",
      "title": [
        "Notes on Labour Supply"
      ],
      "type": "journal-article",
      "container-title": [
        "Canadian Journal of Economics and Political Science"
      ],
      "subject": [],
      "abstract": "",
      "publication_date": "1950-05"
    },
    {
      "doi": "10.1002/j.1551-8833.1950.tb16367.x",
      "title": [
        "Chlorine Demand Constants of Detroit's Water Supply"
      ],
      "type": "journal-article",
      "container-title": [
        "Journal AWWA"
      ],
      "subject": [],
      "abstract": "",
      "publication_date": "1950-05"
    },
    {
      "doi": "10.1021/cen-v028n019.ifc",
      "title": [
        "STOP \"DRIFT\" ERRORS IN Spectrophotometer Readings WITH THE FISHER Power Supply Unit"
      ],
      "type": "journal-article",
      "container-title": [
        "Chemical &amp; Engineering News Archive"
      ],
      "subject": [],
      "abstract": "",
      "publication_date": "1950-05"
    },
    {
      "doi": "10.1111/j.1559-3584.1950.tb02841.x",
      "title": [
        "ATOMIC POWER AND FUEL SUPPLY"
      ],
      "type": "journal-article",
      "container-title": [
        "Journal of the American Society for Naval Engineers"
      ],
      "subject": [],
      "abstract": "",
      "publication_date": "1950-05"
    },
    {
      "doi": "10.1111/j.1096-3642.1950.tb01465.x",
      "title": [
        "The blood supply of the mesonephros of the sheep"
      ],
      "type": "journal-article",
      "container-title": [
        "Proceedings of the Zoological Society of London"
      ],
      "subject": [],
      "abstract": "<jats:title>Summary.</jats:title><jats:p>The extrinsic and intrinsic blood vessels of the mesonephros in the sheep have been studied with special reference to the so‐called “giant glomerulus”. The latter is precocious in its development as compared with the Malpighian bodies caudal to it. The angioblastic preglomerular tissue is the important factor in determining the shape and vascular connexions of the Malpighian bodies. The latter vary greatly in size and shape, possess multiple efferent vessels and show a marked degree of linkage and fusion together. The tubules are surrounded by a plexus of sinusoidal veins in which feature the mesonephros differs fundamentally from the metanephros.</jats:p><jats:p>The early vessels of the metanephros and the origin of the renal and spermatic arteries are briefly discussed.</jats:p>",
      "publication_date": "1950-05"
    },
    {
      "doi": "10.2105/ajph.40.5_pt_2.110",
      "title": [
        "Engineering Section"
      ],
      "type": "journal-article",
      "container-title": [
        "American Journal of Public Health and the Nations Health"
      ],
      "subject": [],
      "abstract": "",
      "publication_date": "1950-05"
    }
  ]
}