{
  "term": "Scenario",
  "total_results": 7,
  "processed_count": 7,
  "discarded_count": 0,
  "items": [
    {
      "doi": "10.1016/0024-6301(90)90362-8",
      "title": [
        "Scenario planning for Norwegian oil and gas"
      ],
      "type": "journal-article",
      "container-title": [
        "Long Range Planning"
      ],
      "subject": [],
      "abstract": "",
      "publication_date": "1990-10"
    },
    {
      "doi": "10.1093/ajhp/47.10.2260",
      "title": [
        "Ethical dimensions of patient drug charges. Scenario"
      ],
      "type": "journal-article",
      "container-title": [
        "American Journal of Health-System Pharmacy"
      ],
      "subject": [],
      "abstract": "",
      "publication_date": "1990-10"
    },
    {
      "doi": "10.33137/q.i..v11i2.10579",
      "title": [
        "On the Clauses in a Scenario of Flaminio Scala"
      ],
      "type": "journal-article",
      "container-title": [
        "Quaderni d'italianistica"
      ],
      "subject": [],
      "abstract": ""
    },
    {
      "doi": "10.1016/0950-5849(90)90143-f",
      "title": [
        "Setting software requirements: scenario for future fighters"
      ],
      "type": "journal-article",
      "container-title": [
        "Information and Software Technology"
      ],
      "subject": [],
      "abstract": "",
      "publication_date": "1990-10"
    },
    {
      "doi": "10.1007/bf02827325",
      "title": [
        "Some remarks on a scenario of supersymmetry in quantum mechanics"
      ],
      "type": "journal-article",
      "container-title": [
        "Il Nuovo Cimento B"
      ],
      "subject": [],
      "abstract": "",
      "publication_date": "1990-10"
    },
    {
      "doi": "10.1086/185843",
      "title": [
        "The universe in a box - Thermal effects in the standard cold dark matter scenario"
      ],
      "type": "journal-article",
      "container-title": [
        "The Astrophysical Journal"
      ],
      "subject": [],
      "abstract": "",
      "publication_date": "1990-10"
    },
    {
      "doi": "10.1016/0924-2716(90)90026-8",
      "title": [
        "Volcano-tectonic scenario of Vulsini volcanoes (Central Italy) from LANDSAT-MSS images and digital elevation data"
      ],
      "type": "journal-article",
      "container-title": [
        "ISPRS Journal of Photogrammetry and Remote Sensing"
      ],
      "subject": [],
      "abstract": "",
      "publication_date": "1990-10"
    }
  ]
}